README.md
setup.cfg
setup.py
asteria/__init__.py
asteria/__main__.py
asteria/asdl.txt
asteria/asteria.py
asteria.egg-info/PKG-INFO
asteria.egg-info/SOURCES.txt
asteria.egg-info/dependency_links.txt
asteria.egg-info/entry_points.txt
asteria.egg-info/top_level.txt