Metadata-Version: 2.1
Name: asteria
Version: 0.0.2
Summary: Missing AST features
Home-page: https://github.com/isidentical/asteria
Author: isidentical
License: UNKNOWN
Platform: UNKNOWN
Requires-Python: >=3.9
